{"status": 0, "uuid": "1134b6c7-236d-4a42-b83b-d32e8cfbb1b4", "zipcode": 75, "statecode": "10", "agencies": [{"status": 0, "uuid": "ba203e33-5c37-4d70-8c50-ca7e07eb299b", "agency_id": "47461", "agency_address": "", "agency_code": "50"}, {"status": 0, "uuid": "b7ffed39-ef7a-4686-b685-4985063cbdda", "agency_id": "48728", "agency_address": "", "agency_code": "46"}, {"status": 0, "uuid": "d5897e60-8209-48ad-9f75-8f992264bb63", "agency_id": "72697", "agency_address": "", "agency_code": "03"}, {"status": 0, "uuid": "3490d2bc-090a-4ec1-9ec6-47a35c141858", "agency_id": "30078", "agency_address": "", "agency_code": "24"}, {"status": 0, "uuid": "0b474c39-75e1-4172-a237-461f4f198019", "agency_id": "73738", "agency_address": "", "agency_code": "99"}, {"status": 0, "uuid": "f045ceeb-d321-4857-9c19-764160d4adb4", "agency_id": "12126", "agency_address": "", "agency_code": "31"}, {"status": 0, "uuid": "e425d761-d2b0-4b1d-927a-f86589a93cb5", "agency_id": "34044", "agency_address": "", "agency_code": "91"}, {"status": 0, "uuid": "1852f828-aa94-401e-977e-a4fc1c649373", "agency_id": "78597", "agency_address": "", "agency_code": "66"}, {"status": 0, "uuid": "0a906942-d9d7-4cde-9ec3-53e1877b05d6", "agency_id": "28056", "agency_address": "", "agency_code": "94"}, {"status": 0, "uuid": "0cf001c5-69f4-41c8-abd9-9db38d294c68", "agency_id": "62487", "agency_address": "", "agency_code": "40"}, {"status": 0, "uuid": "6012a547-6f21-4dfb-8585-7baf66480e5a", "agency_id": "01633", "agency_address": "", "agency_code": "55"}, {"status": 0, "uuid": "8d5df5f4-b61b-4ef8-8db9-5ead025c8690", "agency_id": "67946", "agency_address": "", "agency_code": "71"}, {"status": 0, "uuid": "607b1204-4822-4d45-91aa-049495b178b8", "agency_id": "23981", "agency_address": "", "agency_code": "72"}, {"status": 0, "uuid": "385a92d5-1dc5-4e79-9c7b-065041f09201", "agency_id": "39287", "agency_address": "", "agency_code": "84"}, {"status": 0, "uuid": "635f1528-2c3f-42ea-a863-a0384dd6742d", "agency_id": "81087", "agency_address": "", "agency_code": "60"}, {"status": 0, "uuid": "b00184ed-b528-4e67-b3fe-c9bdbe0ae6e9", "agency_id": "79948", "agency_address": "", "agency_code": "25"}, {"status": 0, "uuid": "7a8dac14-2df7-452f-8f0c-956102891c02", "agency_id": "57220", "agency_address": "", "agency_code": "42"}, {"status": 0, "uuid": "50533c84-9f5f-401a-b0a2-7a2fa62158b1", "agency_id": "83560", "agency_address": "", "agency_code": "41"}, {"status": 0, "uuid": "5314051d-6953-4703-ad3f-1a42cddffdf6", "agency_id": "60843", "agency_address": "", "agency_code": "83"}, {"status": 0, "uuid": "e112a5d2-e89a-4e01-87eb-61f1ab3ae8f3", "agency_id": "47598", "agency_address": "", "agency_code": "77"}, {"status": 0, "uuid": "30d59217-1025-426e-ac47-a71241171e43", "agency_id": "81715", "agency_address": "", "agency_code": "90"}, {"status": 0, "uuid": "c266cb90-a1dc-4eb8-be71-f4fa30679fc1", "agency_id": "31423", "agency_address": "", "agency_code": "21"}, {"status": 0, "uuid": "fc7efec5-d260-4646-a33a-9d795f810653", "agency_id": "90867", "agency_address": "", "agency_code": "43"}, {"status": 0, "uuid": "0e213bb6-2686-4be9-a8a6-53b7f57246f7", "agency_id": "10500", "agency_address": "", "agency_code": "19"}, {"status": 0, "uuid": "f9b41291-1851-4cb2-ae8c-166674d2a27b", "agency_id": "60299", "agency_address": "", "agency_code": "87"}, {"status": 0, "uuid": "1aaaf8fb-5d6b-4348-a94b-465cd5f2382a", "agency_id": "98127", "agency_address": "", "agency_code": "20"}, {"status": 0, "uuid": "da7e6c3e-30fb-4398-81b7-b8c4be03e983", "agency_id": "75157", "agency_address": "", "agency_code": "18"}, {"status": 0, "uuid": "f2f618b0-7c3c-4a7b-acb5-dbd3f1701650", "agency_id": "54705", "agency_address": "", "agency_code": "95"}, {"status": 0, "uuid": "1f5980a3-62ab-49da-983c-4d0ea7cd5441", "agency_id": "96555", "agency_address": "", "agency_code": "61"}, {"status": 0, "uuid": "e3d65033-0872-4cba-b141-8d1d4ceecd97", "agency_id": "84702", "agency_address": "", "agency_code": "37"}, {"status": 0, "uuid": "2b58d7be-b23b-4b2d-9aa7-2b8741c0f800", "agency_id": "83399", "agency_address": "", "agency_code": "10"}, {"status": 0, "uuid": "7251fb4e-d100-407a-be3d-ef6afd0344fc", "agency_id": "31183", "agency_address": "", "agency_code": "35"}, {"status": 0, "uuid": "c7e69974-2c31-4ea2-9699-6c9fc43a3efa", "agency_id": "34828", "agency_address": "", "agency_code": "08"}, {"status": 0, "uuid": "87c87fac-7b07-4ec8-8919-0d832354bd3f", "agency_id": "71508", "agency_address": "", "agency_code": "58"}, {"status": 0, "uuid": "9eaff632-5983-4eb4-94fd-d106fceb79f9", "agency_id": "63678", "agency_address": "", "agency_code": "74"}, {"status": 0, "uuid": "066f2dc5-1600-4c99-ac89-24b4e42d6d17", "agency_id": "48960", "agency_address": "", "agency_code": "98"}, {"status": 0, "uuid": "7e7fee50-0a7a-4022-944d-fa3cc2ceb313", "agency_id": "58955", "agency_address": "", "agency_code": "89"}, {"status": 0, "uuid": "beab2d83-a85e-4e03-9e46-0e3ceb556285", "agency_id": "91597", "agency_address": "", "agency_code": "11"}, {"status": 0, "uuid": "b43f1b23-a322-4cd3-8ce8-e7f9727e8fa8", "agency_id": "30722", "agency_address": "", "agency_code": "65"}, {"status": 0, "uuid": "a1133d40-4015-4200-917e-ded55b048f18", "agency_id": "27146", "agency_address": "", "agency_code": "96"}, {"status": 0, "uuid": "f35f1a4f-3f10-4eeb-9238-78f797ca5515", "agency_id": "53131", "agency_address": "", "agency_code": "97"}, {"status": 0, "uuid": "962b3fc5-a306-44e1-a453-976dede33c48", "agency_id": "24924", "agency_address": "", "agency_code": "93"}, {"status": 0, "uuid": "25391477-61a1-45dd-9055-c9ea54506463", "agency_id": "72045", "agency_address": "", "agency_code": "52"}, {"status": 0, "uuid": "b12c5369-6460-43b9-8ad3-98dbbc4e7f73", "agency_id": "71049", "agency_address": "", "agency_code": "70"}, {"status": 0, "uuid": "fd4f3077-2e19-4efe-a3be-6e4bfa82ccc7", "agency_id": "49821", "agency_address": "", "agency_code": "05"}, {"status": 0, "uuid": "46446105-361b-4726-8665-bb71dcbf85f7", "agency_id": "20292", "agency_address": "", "agency_code": "76"}, {"status": 0, "uuid": "8f20c5e4-cf28-415e-90c9-ffc9b9fee77e", "agency_id": "15850", "agency_address": "", "agency_code": "47"}, {"status": 0, "uuid": "f8d72a35-da37-495c-a2aa-a8326ef7e611", "agency_id": "04805", "agency_address": "", "agency_code": "16"}, {"status": 0, "uuid": "4bd93cd5-38f8-4853-aa7e-6bf74f6e162c", "agency_id": "69522", "agency_address": "", "agency_code": "75"}, {"status": 0, "uuid": "52f80d24-15dc-481d-ba15-158541926483", "agency_id": "97766", "agency_address": "", "agency_code": "26"}, {"status": 0, "uuid": "80b86424-d4f3-470e-b857-65e72c9da527", "agency_id": "86828", "agency_address": "", "agency_code": "17"}, {"status": 0, "uuid": "df302195-ce33-4997-bad4-f42280c5fa73", "agency_id": "30791", "agency_address": "", "agency_code": "23"}, {"status": 0, "uuid": "8c2d24d0-db2e-4f75-ae37-73de1f4cc74e", "agency_id": "32454", "agency_address": "", "agency_code": "27"}, {"status": 0, "uuid": "dc5e30b0-5921-4b84-9008-757de522f6ec", "agency_id": "06891", "agency_address": "", "agency_code": "57"}, {"status": 0, "uuid": "2155ac7c-9bde-48ca-997c-c140871f5d10", "agency_id": "27612", "agency_address": "", "agency_code": "14"}, {"status": 0, "uuid": "deccfc11-9d62-4508-9164-8a98f0d1e626", "agency_id": "56799", "agency_address": "", "agency_code": "64"}, {"status": 0, "uuid": "3e4cc109-f5e0-48ce-8cdd-d1a72821aa14", "agency_id": "54121", "agency_address": "", "agency_code": "48"}, {"status": 0, "uuid": "9cd2a070-6c77-473e-ae99-0e769a235dd2", "agency_id": "41691", "agency_address": "", "agency_code": "38"}, {"status": 0, "uuid": "1b783da2-ddc0-43cd-b851-197d4cb5c346", "agency_id": "76654", "agency_address": "", "agency_code": "85"}, {"status": 0, "uuid": "c935066a-d3f2-4c58-818c-800d1eaf4c07", "agency_id": "46213", "agency_address": "", "agency_code": "07"}, {"status": 0, "uuid": "812b6dde-1f18-43ed-9204-a38698a2f079", "agency_id": "58543", "agency_address": "", "agency_code": "34"}, {"status": 0, "uuid": "64c43e71-af35-4bf2-8afe-d5d527dcc266", "agency_id": "98506", "agency_address": "", "agency_code": "15"}, {"status": 0, "uuid": "b415f450-018b-4ac6-b965-97f08a1efecf", "agency_id": "85852", "agency_address": "", "agency_code": "28"}, {"status": 0, "uuid": "8927e09f-cee3-4f81-a8a1-81bf050b7ee3", "agency_id": "83872", "agency_address": "", "agency_code": "59"}, {"status": 0, "uuid": "e1508b02-aaeb-4dd2-a9d6-83df5e125cd2", "agency_id": "51676", "agency_address": "", "agency_code": "62"}, {"status": 0, "uuid": "b8d8f28b-4c10-4d97-a03f-32eebebfebf5", "agency_id": "27465", "agency_address": "", "agency_code": "92"}, {"status": 0, "uuid": "6c1fcfe9-f7bd-428a-9931-3be5a59a6190", "agency_id": "78759", "agency_address": "", "agency_code": "12"}, {"status": 0, "uuid": "d9210e4c-1d48-46ea-8d65-3769780718ae", "agency_id": "31960", "agency_address": "", "agency_code": "63"}, {"status": 0, "uuid": "817ac9b1-c849-4fd9-a927-742767143d7a", "agency_id": "65461", "agency_address": "", "agency_code": "33"}, {"status": 0, "uuid": "5417bdee-c346-4f9a-94d6-1f76e7522851", "agency_id": "59978", "agency_address": "", "agency_code": "01"}, {"status": 0, "uuid": "27f80770-57b0-4a44-8efa-bfef4673d1c1", "agency_id": "51232", "agency_address": "", "agency_code": "67"}, {"status": 0, "uuid": "d23389c7-e878-4a35-8e1a-ce91b44d0fde", "agency_id": "15469", "agency_address": "", "agency_code": "22"}, {"status": 0, "uuid": "89d16f6c-470b-4f9e-be13-de6208b9f51e", "agency_id": "07812", "agency_address": "", "agency_code": "32"}, {"status": 0, "uuid": "7959ddba-ad56-4d0c-a078-b11226f6021a", "agency_id": "47376", "agency_address": "", "agency_code": "80"}, {"status": 0, "uuid": "3a93f2a1-5dfd-482e-b142-598a2edfce97", "agency_id": "67276", "agency_address": "", "agency_code": "73"}, {"status": 0, "uuid": "890dd84c-e351-4bf4-87dd-1db15c6cf303", "agency_id": "51893", "agency_address": "", "agency_code": "82"}, {"status": 0, "uuid": "9c37dfc7-88ce-48a2-bf8a-9cfdeba1f4d1", "agency_id": "89133", "agency_address": "", "agency_code": "04"}, {"status": 0, "uuid": "aceb6dfb-ed0f-4405-b6e0-ca9f581a1a3d", "agency_id": "15294", "agency_address": "", "agency_code": "86"}, {"status": 0, "uuid": "067ba416-f3ba-45aa-bb7a-565401a86417", "agency_id": "72604", "agency_address": "", "agency_code": "36"}, {"status": 0, "uuid": "9c9a2a34-c984-404e-84bc-216caac0b6ea", "agency_id": "68094", "agency_address": "", "agency_code": "02"}, {"status": 0, "uuid": "7ba382a6-89ed-491f-a756-5f90dd30a407", "agency_id": "57408", "agency_address": "", "agency_code": "51"}, {"status": 0, "uuid": "82416ed6-fabe-4eef-8eca-491dab0c62a6", "agency_id": "79060", "agency_address": "", "agency_code": "09"}, {"status": 0, "uuid": "5a90b051-d27c-41e5-8bc2-3405a1ef5e5c", "agency_id": "84241", "agency_address": "", "agency_code": "44"}, {"status": 0, "uuid": "7911175a-e413-41e1-b0d4-163469660e7f", "agency_id": "48796", "agency_address": "", "agency_code": "49"}, {"status": 0, "uuid": "2f610d0a-2dc6-41f0-9d52-05801cef7b51", "agency_id": "10325", "agency_address": "", "agency_code": "88"}, {"status": 0, "uuid": "bd8d5956-e24b-4884-a372-8e433b64d4c2", "agency_id": "62254", "agency_address": "", "agency_code": "06"}, {"status": 0, "uuid": "4228234d-7aac-46e4-9ec5-d5d3c249f0be", "agency_id": "93510", "agency_address": "", "agency_code": "69"}, {"status": 0, "uuid": "b8163cb0-738f-45f3-b9bd-354a8878afd1", "agency_id": "59993", "agency_address": "", "agency_code": "39"}, {"status": 0, "uuid": "49f5636e-810c-4140-8e8c-74f1c13d57dc", "agency_id": "56362", "agency_address": "", "agency_code": "53"}, {"status": 0, "uuid": "ebcc032a-2145-4d95-aa0a-d2599060f6bf", "agency_id": "42371", "agency_address": "", "agency_code": "13"}, {"status": 0, "uuid": "9ba20b14-6811-400d-a4b0-15f80af7df26", "agency_id": "47931", "agency_address": "", "agency_code": "45"}, {"status": 0, "uuid": "48d1173c-5617-4319-ac45-d729b2a7e649", "agency_id": "90728", "agency_address": "", "agency_code": "30"}, {"status": 0, "uuid": "98e5ab97-dba9-4283-bee5-5979a6c86406", "agency_id": "42070", "agency_address": "", "agency_code": "54"}, {"status": 0, "uuid": "cc280c27-622a-43b5-9e3f-f86b627c53bf", "agency_id": "05249", "agency_address": "", "agency_code": "56"}, {"status": 0, "uuid": "012032d8-5fa1-4826-95d5-e9a19a6952c6", "agency_id": "92149", "agency_address": "", "agency_code": "68"}, {"status": 0, "uuid": "62529e9b-8563-4829-9368-2adbd89a0959", "agency_id": "82170", "agency_address": "", "agency_code": "79"}, {"status": 0, "uuid": "dc7e403a-3373-4fc7-af9e-0c4bad889090", "agency_id": "20723", "agency_address": "", "agency_code": "81"}, {"status": 0, "uuid": "2c0261d8-b46b-47f6-9846-36c86e6f061b", "agency_id": "37185", "agency_address": "", "agency_code": "29"}, {"status": 0, "uuid": "1a5f0a3c-b5e4-4715-9399-85f9e5a23432", "agency_id": "60189", "agency_address": "", "agency_code": "42"}]}