{"status": 0, "uuid": "4fc13245-e4d8-4f0b-92e2-2cea82cc6a34", "zipcode": 3, "statecode": "45", "agencies": [{"status": 0, "uuid": "d867c21c-80c1-43c2-b3ec-ee5e74b3ccd5", "agency_id": "10432", "agency_address": "", "agency_code": "56"}, {"status": 0, "uuid": "2cfd32e4-948e-4883-ade4-6c5fd42e384a", "agency_id": "14166", "agency_address": "", "agency_code": "27"}, {"status": 0, "uuid": "995098fd-47e0-4be4-a0f4-07058220e0ca", "agency_id": "50927", "agency_address": "", "agency_code": "97"}, {"status": 0, "uuid": "242be810-b929-4eed-9942-f49710196c66", "agency_id": "20690", "agency_address": "", "agency_code": "29"}, {"status": 0, "uuid": "8f9331b1-7fa6-4cd0-9836-c989c746ac23", "agency_id": "08287", "agency_address": "", "agency_code": "51"}, {"status": 0, "uuid": "413e4815-8cc8-414c-8ae9-09ed5395944c", "agency_id": "36003", "agency_address": "", "agency_code": "12"}, {"status": 0, "uuid": "12c6b3cf-b1df-4f8b-b586-aa2b00c357c2", "agency_id": "97769", "agency_address": "", "agency_code": "06"}, {"status": 0, "uuid": "7412ab35-b0d4-408e-803c-fd2173c9fae8", "agency_id": "87787", "agency_address": "", "agency_code": "39"}, {"status": 0, "uuid": "33fb3e35-a43a-4ca6-949b-c26681a8b7dd", "agency_id": "89778", "agency_address": "", "agency_code": "08"}, {"status": 0, "uuid": "d6c99d55-ff91-4dd6-922d-626bcb1c27bd", "agency_id": "23758", "agency_address": "", "agency_code": "43"}, {"status": 0, "uuid": "78cff2ae-d0d8-4b61-a5b0-c5c42c246df5", "agency_id": "78723", "agency_address": "", "agency_code": "09"}, {"status": 0, "uuid": "f9723510-3370-49ce-af1f-bcaf1d4a3fad", "agency_id": "13971", "agency_address": "", "agency_code": "26"}, {"status": 0, "uuid": "15ddcd7e-d7ea-48d9-9f8b-09d105a7b3cd", "agency_id": "10319", "agency_address": "", "agency_code": "98"}, {"status": 0, "uuid": "5a5e9550-ef04-4286-a3f8-6876f9e2f214", "agency_id": "27993", "agency_address": "", "agency_code": "48"}, {"status": 0, "uuid": "826360d4-062c-4420-b3af-1361ca4c2db4", "agency_id": "89159", "agency_address": "", "agency_code": "03"}, {"status": 0, "uuid": "89af18f7-e8a2-49db-9b65-4b52391858d4", "agency_id": "25722", "agency_address": "", "agency_code": "44"}, {"status": 0, "uuid": "8706e8d1-c324-44ba-93a5-91a00d7f2455", "agency_id": "86236", "agency_address": "", "agency_code": "40"}, {"status": 0, "uuid": "779c84f9-3e57-4485-8fb9-34c44d6ecb12", "agency_id": "08688", "agency_address": "", "agency_code": "89"}, {"status": 0, "uuid": "642d529a-2ca1-4fb4-a873-4b215b3c4ef9", "agency_id": "18898", "agency_address": "", "agency_code": "47"}, {"status": 0, "uuid": "44babed1-303d-45fb-99bb-32709e9554e6", "agency_id": "20552", "agency_address": "", "agency_code": "99"}, {"status": 0, "uuid": "a2feee97-51de-466d-aea9-c92efdea627b", "agency_id": "79589", "agency_address": "", "agency_code": "91"}, {"status": 0, "uuid": "872a7498-99be-4796-aa55-1d4c0600ce3d", "agency_id": "84287", "agency_address": "", "agency_code": "64"}, {"status": 0, "uuid": "b1669888-0349-4185-8720-fbc725360658", "agency_id": "96682", "agency_address": "", "agency_code": "81"}, {"status": 0, "uuid": "50ee4236-0e96-4205-bc59-d12c2577484f", "agency_id": "35890", "agency_address": "", "agency_code": "19"}, {"status": 0, "uuid": "007fc52a-950c-4478-970a-a6d5af6f7426", "agency_id": "06103", "agency_address": "", "agency_code": "23"}, {"status": 0, "uuid": "6ea2802f-b6ad-4a49-b027-9018d6465551", "agency_id": "26105", "agency_address": "", "agency_code": "88"}, {"status": 0, "uuid": "fcb359b4-9ea2-4984-b90c-993983fdb461", "agency_id": "28569", "agency_address": "", "agency_code": "55"}, {"status": 0, "uuid": "04d7e4ae-e8a4-4eb9-9784-bf0ff79d1dd4", "agency_id": "40037", "agency_address": "", "agency_code": "11"}, {"status": 0, "uuid": "620b713b-889c-491f-94a9-1609e00ab72d", "agency_id": "64740", "agency_address": "", "agency_code": "87"}, {"status": 0, "uuid": "7414fc89-d200-446a-ba36-55bc48c1aa08", "agency_id": "32441", "agency_address": "", "agency_code": "63"}, {"status": 0, "uuid": "759f49d3-ad45-4cbc-9aa7-3610dabd9bb2", "agency_id": "63050", "agency_address": "", "agency_code": "85"}, {"status": 0, "uuid": "3e076cc4-6d7d-4850-9867-07f44752bb94", "agency_id": "70699", "agency_address": "", "agency_code": "10"}, {"status": 0, "uuid": "4ebf4e12-4131-4ebb-9809-6c7543be6ec7", "agency_id": "35485", "agency_address": "", "agency_code": "58"}, {"status": 0, "uuid": "48cc888f-461f-458c-a92f-98069b437d38", "agency_id": "38879", "agency_address": "", "agency_code": "18"}, {"status": 0, "uuid": "666e8415-0b3a-4f4c-95fb-2be377f4abe4", "agency_id": "96865", "agency_address": "", "agency_code": "96"}, {"status": 0, "uuid": "e9de55ef-b1c7-4ad2-af08-0ac3c03001b0", "agency_id": "74960", "agency_address": "", "agency_code": "45"}, {"status": 0, "uuid": "3ac5442c-2202-4f7d-bcb2-95b57f1bea55", "agency_id": "21860", "agency_address": "", "agency_code": "25"}, {"status": 0, "uuid": "19fc956f-5db2-4ea3-92da-c377f17e56cd", "agency_id": "19278", "agency_address": "", "agency_code": "71"}, {"status": 0, "uuid": "e22c344a-f563-46a4-9ea5-2dd200234efd", "agency_id": "83391", "agency_address": "", "agency_code": "17"}, {"status": 0, "uuid": "6cc6bbd0-0440-4ee2-b95a-92cc0b180142", "agency_id": "01215", "agency_address": "", "agency_code": "42"}, {"status": 0, "uuid": "0a5cdcd4-3ea7-494f-a050-0a4df82d8cd9", "agency_id": "76695", "agency_address": "", "agency_code": "68"}, {"status": 0, "uuid": "a676ad26-e802-4add-9eeb-abc72a8c2883", "agency_id": "87958", "agency_address": "", "agency_code": "69"}, {"status": 0, "uuid": "83f47aef-c8c4-4e36-bf99-fe30f676af19", "agency_id": "48299", "agency_address": "", "agency_code": "94"}, {"status": 0, "uuid": "9b1ccd06-bc57-4617-a4de-f370845423f6", "agency_id": "28966", "agency_address": "", "agency_code": "73"}, {"status": 0, "uuid": "8a800ec7-f5cb-4a87-adf4-89eb8eaa2cb9", "agency_id": "96846", "agency_address": "", "agency_code": "54"}, {"status": 0, "uuid": "ed244641-f2f3-43e3-918b-329087534105", "agency_id": "86294", "agency_address": "", "agency_code": "22"}, {"status": 0, "uuid": "37092e2f-42d5-4032-a90e-700d9a60b8a3", "agency_id": "80798", "agency_address": "", "agency_code": "84"}, {"status": 0, "uuid": "6c811490-7fe5-41b0-8766-28dc3da20ef8", "agency_id": "15619", "agency_address": "", "agency_code": "79"}, {"status": 0, "uuid": "9f0f03c6-155e-4964-9957-53ac9176f1ef", "agency_id": "21480", "agency_address": "", "agency_code": "49"}, {"status": 0, "uuid": "478b62ad-5ea3-4604-b92e-c10a5c3a159c", "agency_id": "72273", "agency_address": "", "agency_code": "60"}, {"status": 0, "uuid": "903d4ac1-2727-4912-9b9b-40c77b489eb8", "agency_id": "51957", "agency_address": "", "agency_code": "21"}, {"status": 0, "uuid": "a3c1566c-6bc0-4731-a885-68902bb792dd", "agency_id": "92161", "agency_address": "", "agency_code": "83"}, {"status": 0, "uuid": "4b213a22-42e4-4787-87d2-e17bfe59b9a8", "agency_id": "73853", "agency_address": "", "agency_code": "57"}, {"status": 0, "uuid": "afbb45ad-ae22-4044-86d2-e27ab0f58e84", "agency_id": "20665", "agency_address": "", "agency_code": "34"}, {"status": 0, "uuid": "7822081c-3f43-4cb2-99dc-793d45e73889", "agency_id": "73099", "agency_address": "", "agency_code": "92"}, {"status": 0, "uuid": "f950bf81-1e57-4c67-9e65-344612d62e14", "agency_id": "56046", "agency_address": "", "agency_code": "78"}, {"status": 0, "uuid": "a8461583-3a34-49ca-b586-807b94ff2c42", "agency_id": "94500", "agency_address": "", "agency_code": "16"}, {"status": 0, "uuid": "a640f826-218f-49cd-8988-12dc5cbe2153", "agency_id": "53765", "agency_address": "", "agency_code": "32"}, {"status": 0, "uuid": "e86d3b8c-3834-476d-8a4d-b87b52c96ec7", "agency_id": "15248", "agency_address": "", "agency_code": "76"}, {"status": 0, "uuid": "cf622dcd-e9de-45bb-ad52-773db7dd7d3a", "agency_id": "94241", "agency_address": "", "agency_code": "75"}, {"status": 0, "uuid": "faee48bc-513a-4b86-93d2-6a5caee54f86", "agency_id": "73985", "agency_address": "", "agency_code": "33"}, {"status": 0, "uuid": "8fca8fd5-1743-4efb-94e9-deeb47400d9c", "agency_id": "75277", "agency_address": "", "agency_code": "01"}, {"status": 0, "uuid": "e0adb9d2-ffe6-4b58-9e1d-be26bf562480", "agency_id": "70849", "agency_address": "", "agency_code": "95"}, {"status": 0, "uuid": "8991d1d1-3f68-450c-a585-78bb36540fc3", "agency_id": "87900", "agency_address": "", "agency_code": "72"}, {"status": 0, "uuid": "1c14c6e7-8954-4400-972e-57c144d146ed", "agency_id": "81333", "agency_address": "", "agency_code": "07"}, {"status": 0, "uuid": "3e514eea-1292-4803-bd54-3bb42895441d", "agency_id": "45559", "agency_address": "", "agency_code": "61"}, {"status": 0, "uuid": "b68d6799-b284-403f-b805-d4140bff257d", "agency_id": "61118", "agency_address": "", "agency_code": "67"}, {"status": 0, "uuid": "1cdcedcb-022a-405c-98de-05bdcf16e86f", "agency_id": "80905", "agency_address": "", "agency_code": "04"}, {"status": 0, "uuid": "aa1ba3a0-1b24-4387-b40f-72d5413849ee", "agency_id": "78797", "agency_address": "", "agency_code": "86"}, {"status": 0, "uuid": "21170bfd-3c7a-490f-88c0-ac99770670c9", "agency_id": "46226", "agency_address": "", "agency_code": "93"}, {"status": 0, "uuid": "8896e997-89eb-4f41-91c8-92a4a18766dd", "agency_id": "43205", "agency_address": "", "agency_code": "82"}, {"status": 0, "uuid": "91a2af4b-fb94-417c-9e0b-380762106cc8", "agency_id": "15043", "agency_address": "", "agency_code": "30"}, {"status": 0, "uuid": "727a1da7-8893-4964-aef8-e2c1bc98b569", "agency_id": "94363", "agency_address": "", "agency_code": "14"}, {"status": 0, "uuid": "6c8f30e8-b6f7-4b99-a655-5c4bb7a855b4", "agency_id": "10227", "agency_address": "", "agency_code": "05"}, {"status": 0, "uuid": "879c1c82-76cd-4aa9-95f7-0cf506f18b0e", "agency_id": "68061", "agency_address": "", "agency_code": "31"}, {"status": 0, "uuid": "41db730b-b49e-482e-a066-07561f184b59", "agency_id": "64685", "agency_address": "", "agency_code": "65"}, {"status": 0, "uuid": "75883001-7d48-4492-911d-67177de45a96", "agency_id": "97153", "agency_address": "", "agency_code": "35"}, {"status": 0, "uuid": "7674f937-c5e1-409d-83df-8a5f97a0187d", "agency_id": "16578", "agency_address": "", "agency_code": "41"}, {"status": 0, "uuid": "98770d27-6a52-4b45-8b32-3b13115184f1", "agency_id": "48947", "agency_address": "", "agency_code": "66"}, {"status": 0, "uuid": "8507b176-c5d9-4009-8ec4-e8b19c8429b0", "agency_id": "84039", "agency_address": "", "agency_code": "02"}, {"status": 0, "uuid": "e3150bfe-bd90-43f1-9c3c-2a38907658a8", "agency_id": "24298", "agency_address": "", "agency_code": "52"}, {"status": 0, "uuid": "91e4c344-22cf-42f6-928d-1a89827bc6ce", "agency_id": "28322", "agency_address": "", "agency_code": "15"}, {"status": 0, "uuid": "c767c825-9b54-49c9-8e6e-04bdd65abb79", "agency_id": "70466", "agency_address": "", "agency_code": "36"}, {"status": 0, "uuid": "633da981-8392-48d4-ace9-34fd25949199", "agency_id": "98421", "agency_address": "", "agency_code": "20"}, {"status": 0, "uuid": "8c6159d8-09c5-4d96-b555-235fe98d7749", "agency_id": "58060", "agency_address": "", "agency_code": "53"}, {"status": 0, "uuid": "23d03ee5-6c40-4588-974f-fcaabfb5e260", "agency_id": "52341", "agency_address": "", "agency_code": "62"}, {"status": 0, "uuid": "92a3afe0-86f5-4ab9-9062-91e1ef2ad6fe", "agency_id": "10425", "agency_address": "", "agency_code": "50"}, {"status": 0, "uuid": "af0371b0-5c0e-4630-86ad-3bc535850c50", "agency_id": "25819", "agency_address": "", "agency_code": "90"}, {"status": 0, "uuid": "16e0ad32-ece9-4262-9856-c9a7c1b8fcf2", "agency_id": "83737", "agency_address": "", "agency_code": "38"}, {"status": 0, "uuid": "3be7ca89-4f85-473d-9c66-07e991f51ddd", "agency_id": "04131", "agency_address": "", "agency_code": "37"}, {"status": 0, "uuid": "42402bc4-75f2-40f9-871e-e0c97876edcd", "agency_id": "49197", "agency_address": "", "agency_code": "46"}, {"status": 0, "uuid": "caeaa21f-83cb-4a04-91aa-a19042ebfba8", "agency_id": "87990", "agency_address": "", "agency_code": "70"}, {"status": 0, "uuid": "fa7da930-1fdb-4b5b-9d51-c889794f9f10", "agency_id": "73039", "agency_address": "", "agency_code": "13"}, {"status": 0, "uuid": "0535bdd3-4e63-4696-b83f-a7ccd6ef35aa", "agency_id": "91943", "agency_address": "", "agency_code": "77"}, {"status": 0, "uuid": "83734502-7ee7-4986-9c12-67647ab39cc0", "agency_id": "83523", "agency_address": "", "agency_code": "74"}, {"status": 0, "uuid": "4aee7501-7d00-4bef-af05-16cdf0533aab", "agency_id": "28815", "agency_address": "", "agency_code": "24"}, {"status": 0, "uuid": "f3d952d6-045d-489a-8656-53164ba1ac40", "agency_id": "87646", "agency_address": "", "agency_code": "59"}, {"status": 0, "uuid": "edcd20ba-c86d-40ea-bf45-757c3d4bca75", "agency_id": "64507", "agency_address": "", "agency_code": "80"}, {"status": 0, "uuid": "f620729a-5843-4827-b634-066a40b32bcd", "agency_id": "48492", "agency_address": "", "agency_code": "78"}]}