{
                "status": 0,
                "uuid": "6b2efb8e-411a-4aab-82fa-6c42e50eeea6",
                "zipcode": 61,
                "statecode": "34",
                "agencies": [
                                {
                                                "status": 0,
                                                "uuid": "c8fb164f-aeba-45ce-b009-12d7c23ba80b",
                                                "agency_id": "50550",
                                                "agency_address": "",
                                                "agency_code": "42"
                                },
                                {
                                                "status": 0,
                                                "uuid": "cb2c6a7d-5023-4267-968b-43defa83d744",
                                                "agency_id": "76465",
                                                "agency_address": "",
                                                "agency_code": "84"
                                },
                                {
                                                "status": 0,
                                                "uuid": "88a18cb2-adc6-4540-b0b2-09456066e2cf",
                                                "agency_id": "17043",
                                                "agency_address": "",
                                                "agency_code": "41"
                                },
                                {
                                                "status": 0,
                                                "uuid": "3899dc4c-ab4e-468b-931e-7a139c2099f8",
                                                "agency_id": "29517",
                                                "agency_address": "",
                                                "agency_code": "99"
                                },
                                {
                                                "status": 0,
                                                "uuid": "13e429e6-708f-4f41-80c3-239d9aa0d680",
                                                "agency_id": "63337",
                                                "agency_address": "",
                                                "agency_code": "50"
                                },
                                {
                                                "status": 0,
                                                "uuid": "c1ee3b9e-291d-4181-8139-0f635ea7e0cd",
                                                "agency_id": "48096",
                                                "agency_address": "",
                                                "agency_code": "68"
                                },
                                {
                                                "status": 0,
                                                "uuid": "56ef688b-8dbb-477b-acd8-3b176cb774d2",
                                                "agency_id": "07699",
                                                "agency_address": "",
                                                "agency_code": "53"
                                },
                                {
                                                "status": 0,
                                                "uuid": "68a91cdc-8f2f-4f7c-86b6-ecd9518b8a7a",
                                                "agency_id": "60149",
                                                "agency_address": "",
                                                "agency_code": "39"
                                },
                                {
                                                "status": 0,
                                                "uuid": "a3e27e2a-5189-4395-911d-c8c1dca65fed",
                                                "agency_id": "38785",
                                                "agency_address": "",
                                                "agency_code": "88"
                                },
                                {
                                                "status": 0,
                                                "uuid": "99095c61-cc9c-4b86-abdb-0eba1af62c53",
                                                "agency_id": "36727",
                                                "agency_address": "",
                                                "agency_code": "59"
                                },
                                {
                                                "status": 0,
                                                "uuid": "328df6be-6c9a-4942-ad48-68a022592b35",
                                                "agency_id": "26606",
                                                "agency_address": "",
                                                "agency_code": "80"
                                },
                                {
                                                "status": 0,
                                                "uuid": "b13bd595-106b-493c-83a5-ddfcfebb948d",
                                                "agency_id": "84046",
                                                "agency_address": "",
                                                "agency_code": "33"
                                },
                                {
                                                "status": 0,
                                                "uuid": "e21db1d2-bd36-41ba-8ee0-6bcb26f67fc1",
                                                "agency_id": "26871",
                                                "agency_address": "",
                                                "agency_code": "51"
                                },
                                {
                                                "status": 0,
                                                "uuid": "2db00e90-f233-47b5-8d64-ba50f3fa1f01",
                                                "agency_id": "38359",
                                                "agency_address": "",
                                                "agency_code": "82"
                                },
                                {
                                                "status": 0,
                                                "uuid": "1b46c24c-b650-475a-8b94-0c682e455e53",
                                                "agency_id": "18783",
                                                "agency_address": "",
                                                "agency_code": "54"
                                },
                                {
                                                "status": 0,
                                                "uuid": "1cf54b10-1d5c-457b-aff0-4385c4d96a12",
                                                "agency_id": "57620",
                                                "agency_address": "",
                                                "agency_code": "61"
                                },
                                {
                                                "status": 0,
                                                "uuid": "71313e7d-1255-4f07-8021-2471c4c79e52",
                                                "agency_id": "87350",
                                                "agency_address": "",
                                                "agency_code": "92"
                                },
                                {
                                                "status": 0,
                                                "uuid": "c0d31f66-6e23-4b23-a234-56cd58d4597a",
                                                "agency_id": "74099",
                                                "agency_address": "",
                                                "agency_code": "65"
                                },
                                {
                                                "status": 0,
                                                "uuid": "babdd570-4556-49a4-8ee8-a67395f68fb6",
                                                "agency_id": "30864",
                                                "agency_address": "",
                                                "agency_code": "08"
                                },
                                {
                                                "status": 0,
                                                "uuid": "f64d64af-dd80-42bd-a0bd-576f63e7c08d",
                                                "agency_id": "91674",
                                                "agency_address": "",
                                                "agency_code": "62"
                                },
                                {
                                                "status": 0,
                                                "uuid": "3ab67acd-b7ba-40f8-b01d-923f3a570319",
                                                "agency_id": "67637",
                                                "agency_address": "",
                                                "agency_code": "75"
                                },
                                {
                                                "status": 0,
                                                "uuid": "65a8c8b9-013a-49dc-a340-4211bfdd39b0",
                                                "agency_id": "26413",
                                                "agency_address": "",
                                                "agency_code": "46"
                                },
                                {
                                                "status": 0,
                                                "uuid": "5b7b0687-1f3b-463b-bcbb-ed977b594d4a",
                                                "agency_id": "62412",
                                                "agency_address": "",
                                                "agency_code": "35"
                                },
                                {
                                                "status": 0,
                                                "uuid": "14d1a5a6-0dcc-4a0d-b981-e27cabb1dbff",
                                                "agency_id": "85128",
                                                "agency_address": "",
                                                "agency_code": "27"
                                },
                                {
                                                "status": 0,
                                                "uuid": "7e75f194-5f3c-4684-8f5b-51a10ea5a4af",
                                                "agency_id": "12129",
                                                "agency_address": "",
                                                "agency_code": "32"
                                },
                                {
                                                "status": 0,
                                                "uuid": "3d8ead03-b8a7-449e-b1f1-792bcddb450f",
                                                "agency_id": "67826",
                                                "agency_address": "",
                                                "agency_code": "23"
                                },
                                {
                                                "status": 0,
                                                "uuid": "5d32bbac-d73c-4a3c-a96e-9bdce59c1e51",
                                                "agency_id": "30969",
                                                "agency_address": "",
                                                "agency_code": "77"
                                },
                                {
                                                "status": 0,
                                                "uuid": "89af1d86-2697-4c9a-8238-7e7537aa8107",
                                                "agency_id": "96387",
                                                "agency_address": "",
                                                "agency_code": "26"
                                },
                                {
                                                "status": 0,
                                                "uuid": "30d4b68d-b951-4ec4-a65f-5f31dfbb6ca4",
                                                "agency_id": "10214",
                                                "agency_address": "",
                                                "agency_code": "71"
                                },
                                {
                                                "status": 0,
                                                "uuid": "058991ec-fa4e-40c0-8fe7-7e0391ff1cd1",
                                                "agency_id": "74175",
                                                "agency_address": "",
                                                "agency_code": "74"
                                },
                                {
                                                "status": 0,
                                                "uuid": "0c6fd25f-4da2-48f0-8e09-4838cec39a04",
                                                "agency_id": "68470",
                                                "agency_address": "",
                                                "agency_code": "28"
                                },
                                {
                                                "status": 0,
                                                "uuid": "43631d31-f0cf-4c85-8741-6c4d6cbb5ab3",
                                                "agency_id": "57779",
                                                "agency_address": "",
                                                "agency_code": "10"
                                },
                                {
                                                "status": 0,
                                                "uuid": "4c3e19d8-abc8-424c-b7b4-8c137a81b1c0",
                                                "agency_id": "10174",
                                                "agency_address": "",
                                                "agency_code": "95"
                                },
                                {
                                                "status": 0,
                                                "uuid": "88770fc7-fc85-4733-8ad9-64c177b0dca8",
                                                "agency_id": "38918",
                                                "agency_address": "",
                                                "agency_code": "47"
                                },
                                {
                                                "status": 0,
                                                "uuid": "7cc9798a-3634-4161-a5e7-fc5c4c9d2c50",
                                                "agency_id": "26925",
                                                "agency_address": "",
                                                "agency_code": "17"
                                },
                                {
                                                "status": 0,
                                                "uuid": "bd8a5fdc-23c0-474c-a778-c8660e8cd445",
                                                "agency_id": "78810",
                                                "agency_address": "",
                                                "agency_code": "79"
                                },
                                {
                                                "status": 0,
                                                "uuid": "1a399f24-092a-42f3-b949-33c702352b61",
                                                "agency_id": "94923",
                                                "agency_address": "",
                                                "agency_code": "37"
                                },
                                {
                                                "status": 0,
                                                "uuid": "3f9cd2c2-3df3-4c68-b289-c8a04ecf00a1",
                                                "agency_id": "81009",
                                                "agency_address": "",
                                                "agency_code": "60"
                                },
                                {
                                                "status": 0,
                                                "uuid": "96e2e0fc-8319-48e3-be80-e424f91d1bf8",
                                                "agency_id": "60644",
                                                "agency_address": "",
                                                "agency_code": "01"
                                },
                                {
                                                "status": 0,
                                                "uuid": "ce8f2585-e9a9-4731-9061-47e799e27db5",
                                                "agency_id": "41802",
                                                "agency_address": "",
                                                "agency_code": "52"
                                },
                                {
                                                "status": 0,
                                                "uuid": "5a7e31c8-bca2-4dcb-b235-026ea40c2e3d",
                                                "agency_id": "57893",
                                                "agency_address": "",
                                                "agency_code": "76"
                                },
                                {
                                                "status": 0,
                                                "uuid": "e8dd7007-7154-4918-93eb-d6c20ad2f95b",
                                                "agency_id": "64204",
                                                "agency_address": "",
                                                "agency_code": "89"
                                },
                                {
                                                "status": 0,
                                                "uuid": "e75f7144-fabb-4b0c-bd7f-928bd1f5ffba",
                                                "agency_id": "29176",
                                                "agency_address": "",
                                                "agency_code": "45"
                                },
                                {
                                                "status": 0,
                                                "uuid": "a35fff61-c6f0-4d1e-84a1-4d855ae70f32",
                                                "agency_id": "76269",
                                                "agency_address": "",
                                                "agency_code": "19"
                                },
                                {
                                                "status": 0,
                                                "uuid": "f1ecb81d-ccad-41d0-b135-44e5fdd004ed",
                                                "agency_id": "03512",
                                                "agency_address": "",
                                                "agency_code": "56"
                                },
                                {
                                                "status": 0,
                                                "uuid": "a5ec72a4-8433-45b9-9801-9655cb09faac",
                                                "agency_id": "23498",
                                                "agency_address": "",
                                                "agency_code": "49"
                                },
                                {
                                                "status": 0,
                                                "uuid": "3b205d3e-9057-48d0-ba15-14645a05ae9b",
                                                "agency_id": "73344",
                                                "agency_address": "",
                                                "agency_code": "07"
                                },
                                {
                                                "status": 0,
                                                "uuid": "7464dc83-8347-41d6-857b-cde37fc923ef",
                                                "agency_id": "54401",
                                                "agency_address": "",
                                                "agency_code": "66"
                                },
                                {
                                                "status": 0,
                                                "uuid": "382bd5af-9069-48d4-a442-108fbd95d9e9",
                                                "agency_id": "32242",
                                                "agency_address": "",
                                                "agency_code": "48"
                                },
                                {
                                                "status": 0,
                                                "uuid": "baa9bf7e-aafd-4d12-bfb4-af2b754cd599",
                                                "agency_id": "48910",
                                                "agency_address": "",
                                                "agency_code": "96"
                                },
                                {
                                                "status": 0,
                                                "uuid": "6cb2bcfd-cacd-40ba-85f9-2918c03c5933",
                                                "agency_id": "27989",
                                                "agency_address": "",
                                                "agency_code": "40"
                                },
                                {
                                                "status": 0,
                                                "uuid": "03864c3e-5451-4044-804d-efa7f321d801",
                                                "agency_id": "10707",
                                                "agency_address": "",
                                                "agency_code": "38"
                                },
                                {
                                                "status": 0,
                                                "uuid": "c09c6620-2fa7-4dac-aad9-9c8036d3809c",
                                                "agency_id": "91251",
                                                "agency_address": "",
                                                "agency_code": "18"
                                },
                                {
                                                "status": 0,
                                                "uuid": "0d4c00a4-6913-4740-9b2d-c5f2b4680d92",
                                                "agency_id": "90183",
                                                "agency_address": "",
                                                "agency_code": "78"
                                },
                                {
                                                "status": 0,
                                                "uuid": "d0d4985b-057e-4cea-a2bd-adede34b08be",
                                                "agency_id": "98603",
                                                "agency_address": "",
                                                "agency_code": "72"
                                },
                                {
                                                "status": 0,
                                                "uuid": "f230eb0f-195d-4411-8128-39571c56e86d",
                                                "agency_id": "19699",
                                                "agency_address": "",
                                                "agency_code": "93"
                                },
                                {
                                                "status": 0,
                                                "uuid": "ac507074-b1bb-4714-8ebe-450fdad2f730",
                                                "agency_id": "78816",
                                                "agency_address": "",
                                                "agency_code": "11"
                                },
                                {
                                                "status": 0,
                                                "uuid": "f4be24a3-86a7-4532-abf4-d64d54c85589",
                                                "agency_id": "43151",
                                                "agency_address": "",
                                                "agency_code": "85"
                                },
                                {
                                                "status": 0,
                                                "uuid": "1bac24ac-c514-473a-96ee-85bd8e97d841",
                                                "agency_id": "68793",
                                                "agency_address": "",
                                                "agency_code": "81"
                                },
                                {
                                                "status": 0,
                                                "uuid": "9b5ca602-e7d1-4950-8b3d-9fd8117b6c3c",
                                                "agency_id": "01768",
                                                "agency_address": "",
                                                "agency_code": "97"
                                },
                                {
                                                "status": 0,
                                                "uuid": "c107ec02-c262-4d8f-ab82-10317e9d44c0",
                                                "agency_id": "38068",
                                                "agency_address": "",
                                                "agency_code": "36"
                                },
                                {
                                                "status": 0,
                                                "uuid": "ae141d21-6107-42ca-a4a7-b960bdc45f22",
                                                "agency_id": "60876",
                                                "agency_address": "",
                                                "agency_code": "31"
                                },
                                {
                                                "status": 0,
                                                "uuid": "4c87369d-9f8c-458a-b7a9-fa0277d57ede",
                                                "agency_id": "25163",
                                                "agency_address": "",
                                                "agency_code": "43"
                                },
                                {
                                                "status": 0,
                                                "uuid": "1ce10922-e5a9-43d2-b369-4526e5e39b5f",
                                                "agency_id": "45986",
                                                "agency_address": "",
                                                "agency_code": "69"
                                },
                                {
                                                "status": 0,
                                                "uuid": "de63af0f-4ab6-476c-8af9-51df2a60b466",
                                                "agency_id": "17154",
                                                "agency_address": "",
                                                "agency_code": "83"
                                },
                                {
                                                "status": 0,
                                                "uuid": "561d0a03-8112-4abd-a7e7-5dec1fe55890",
                                                "agency_id": "56469",
                                                "agency_address": "",
                                                "agency_code": "57"
                                },
                                {
                                                "status": 0,
                                                "uuid": "8b33382d-09b8-4d67-a3f2-2575407b0528",
                                                "agency_id": "84108",
                                                "agency_address": "",
                                                "agency_code": "30"
                                },
                                {
                                                "status": 0,
                                                "uuid": "2f240c95-b3d9-434f-a4a2-2356ccaf01dc",
                                                "agency_id": "25965",
                                                "agency_address": "",
                                                "agency_code": "55"
                                },
                                {
                                                "status": 0,
                                                "uuid": "bbeb61e4-b3ca-4b2f-bbc9-592ba44068d1",
                                                "agency_id": "05491",
                                                "agency_address": "",
                                                "agency_code": "12"
                                },
                                {
                                                "status": 0,
                                                "uuid": "cb24473f-45e3-42d8-8bc1-3cdfb3e92a82",
                                                "agency_id": "10451",
                                                "agency_address": "",
                                                "agency_code": "20"
                                },
                                {
                                                "status": 0,
                                                "uuid": "03167ed3-e16f-4c6a-9535-e42d53b7eac3",
                                                "agency_id": "46125",
                                                "agency_address": "",
                                                "agency_code": "34"
                                },
                                {
                                                "status": 0,
                                                "uuid": "dd4976f3-fc68-4a41-9ab8-671e373f3339",
                                                "agency_id": "76041",
                                                "agency_address": "",
                                                "agency_code": "21"
                                },
                                {
                                                "status": 0,
                                                "uuid": "c0d54030-5a69-4b48-bf40-77aeeff52cda",
                                                "agency_id": "74487",
                                                "agency_address": "",
                                                "agency_code": "90"
                                },
                                {
                                                "status": 0,
                                                "uuid": "a4e7e62f-0990-47e2-9407-c24d0a2491d1",
                                                "agency_id": "42806",
                                                "agency_address": "",
                                                "agency_code": "13"
                                },
                                {
                                                "status": 0,
                                                "uuid": "4705f0ac-ad76-476c-8822-9e970454f5f7",
                                                "agency_id": "01741",
                                                "agency_address": "",
                                                "agency_code": "58"
                                },
                                {
                                                "status": 0,
                                                "uuid": "c145e154-3450-49dd-a772-a518e5b8487f",
                                                "agency_id": "76296",
                                                "agency_address": "",
                                                "agency_code": "94"
                                },
                                {
                                                "status": 0,
                                                "uuid": "4778ddff-c46f-4fe5-808a-3b0068ebfbde",
                                                "agency_id": "60654",
                                                "agency_address": "",
                                                "agency_code": "29"
                                },
                                {
                                                "status": 0,
                                                "uuid": "bae97cbb-c306-4d98-9e39-d00744cd3230",
                                                "agency_id": "46031",
                                                "agency_address": "",
                                                "agency_code": "14"
                                },
                                {
                                                "status": 0,
                                                "uuid": "36496db9-e5cb-4b6e-a89f-b146954bc01a",
                                                "agency_id": "64447",
                                                "agency_address": "",
                                                "agency_code": "64"
                                },
                                {
                                                "status": 0,
                                                "uuid": "d0298ed8-d581-44dc-8b1d-61f554569bdb",
                                                "agency_id": "01405",
                                                "agency_address": "",
                                                "agency_code": "09"
                                },
                                {
                                                "status": 0,
                                                "uuid": "d4eacf1b-f1f6-4e28-bedf-4c8d5cc43943",
                                                "agency_id": "74176",
                                                "agency_address": "",
                                                "agency_code": "73"
                                },
                                {
                                                "status": 0,
                                                "uuid": "1e72d4f1-0dd9-4973-a40e-6c6188b8d1db",
                                                "agency_id": "32771",
                                                "agency_address": "",
                                                "agency_code": "06"
                                },
                                {
                                                "status": 0,
                                                "uuid": "9a3211f6-de6e-4540-b3ed-65901194fa62",
                                                "agency_id": "73613",
                                                "agency_address": "",
                                                "agency_code": "70"
                                },
                                {
                                                "status": 0,
                                                "uuid": "a054c814-2f32-48e0-96e9-561ab5ca137f",
                                                "agency_id": "21756",
                                                "agency_address": "",
                                                "agency_code": "16"
                                },
                                {
                                                "status": 0,
                                                "uuid": "5cd975f1-d056-4094-a359-8b5dce849eb1",
                                                "agency_id": "47530",
                                                "agency_address": "",
                                                "agency_code": "05"
                                },
                                {
                                                "status": 0,
                                                "uuid": "6e5c8cd2-e3ea-4ea3-9d54-72105de10259",
                                                "agency_id": "18040",
                                                "agency_address": "",
                                                "agency_code": "02"
                                },
                                {
                                                "status": 0,
                                                "uuid": "8674e475-b5e2-416b-a788-50250f652f0d",
                                                "agency_id": "58818",
                                                "agency_address": "",
                                                "agency_code": "87"
                                },
                                {
                                                "status": 0,
                                                "uuid": "979f74b8-5e5c-48b3-8d3d-c77d8bd01ead",
                                                "agency_id": "94289",
                                                "agency_address": "",
                                                "agency_code": "44"
                                },
                                {
                                                "status": 0,
                                                "uuid": "f5e18282-a8d7-497e-a90e-840f57c1e60b",
                                                "agency_id": "60286",
                                                "agency_address": "",
                                                "agency_code": "98"
                                },
                                {
                                                "status": 0,
                                                "uuid": "a7df7b3a-5485-4da9-a735-f91b09a8ff10",
                                                "agency_id": "87337",
                                                "agency_address": "",
                                                "agency_code": "25"
                                },
                                {
                                                "status": 0,
                                                "uuid": "85668f37-ca27-4d59-a166-67a48114b6c0",
                                                "agency_id": "15714",
                                                "agency_address": "",
                                                "agency_code": "04"
                                },
                                {
                                                "status": 0,
                                                "uuid": "294eedf8-bc86-48ff-9f77-5da0cef81383",
                                                "agency_id": "40223",
                                                "agency_address": "",
                                                "agency_code": "24"
                                },
                                {
                                                "status": 0,
                                                "uuid": "fac8b437-2429-4518-9836-b1cb29f173c4",
                                                "agency_id": "89481",
                                                "agency_address": "",
                                                "agency_code": "86"
                                },
                                {
                                                "status": 0,
                                                "uuid": "cba790ae-d8f6-43cc-8003-856a7bf33c5c",
                                                "agency_id": "46750",
                                                "agency_address": "",
                                                "agency_code": "22"
                                },
                                {
                                                "status": 0,
                                                "uuid": "9a41f463-9edc-4ae1-87bc-d52cc838c329",
                                                "agency_id": "68583",
                                                "agency_address": "",
                                                "agency_code": "91"
                                },
                                {
                                                "status": 0,
                                                "uuid": "c1030c65-3327-46c2-9ec6-9e04f169a3dd",
                                                "agency_id": "03099",
                                                "agency_address": "",
                                                "agency_code": "15"
                                },
                                {
                                                "status": 0,
                                                "uuid": "96fcfb4e-3fc8-47a2-a2bf-5426cab46fc1",
                                                "agency_id": "09618",
                                                "agency_address": "",
                                                "agency_code": "03"
                                },
                                {
                                                "status": 0,
                                                "uuid": "b052a8db-03c0-4478-ad6f-5ff3b97ea179",
                                                "agency_id": "34000",
                                                "agency_address": "",
                                                "agency_code": "63"
                                },
                                {
                                                "status": 0,
                                                "uuid": "8f5160e7-fe6c-4753-a6c0-4bab99712b67",
                                                "agency_id": "81148",
                                                "agency_address": "",
                                                "agency_code": "96"
                                }
                ]
}