{"status": 0, "uuid": "9d65589c-17a4-4458-bef9-5963a8b64ee3", "zipcode": 27, "statecode": "49", "agencies": [{"status": 0, "uuid": "573ada3e-6112-473d-a321-a95817c1ef37", "agency_id": "05213", "agency_address": "", "agency_code": "93"}, {"status": 0, "uuid": "742e09a4-09bf-4160-870a-2e91636dc36a", "agency_id": "73909", "agency_address": "", "agency_code": "32"}, {"status": 0, "uuid": "7a80ec66-db65-40f4-8459-9d331c5ea161", "agency_id": "38697", "agency_address": "", "agency_code": "83"}, {"status": 0, "uuid": "a5583fb9-ca21-4653-b398-22cdbd4d1e06", "agency_id": "85762", "agency_address": "", "agency_code": "07"}, {"status": 0, "uuid": "ab29caee-5691-4e7a-9a76-731e6b94803d", "agency_id": "72370", "agency_address": "", "agency_code": "25"}, {"status": 0, "uuid": "d7eeb31a-01ca-4e20-9ce5-713d252549fd", "agency_id": "58306", "agency_address": "", "agency_code": "67"}, {"status": 0, "uuid": "646b44c4-66e9-4651-96b6-eded957fcb5a", "agency_id": "52183", "agency_address": "", "agency_code": "28"}, {"status": 0, "uuid": "a9e92292-efde-4257-852c-917eb685ebfa", "agency_id": "20361", "agency_address": "", "agency_code": "76"}, {"status": 0, "uuid": "cd3a68a9-1a61-4611-aac3-c2459488c8bf", "agency_id": "02599", "agency_address": "", "agency_code": "53"}, {"status": 0, "uuid": "553ceb22-4657-47d4-a953-7212c47a19a4", "agency_id": "65876", "agency_address": "", "agency_code": "57"}, {"status": 0, "uuid": "1549bc2e-dd78-4fa8-bf9d-e98d35d3a836", "agency_id": "27072", "agency_address": "", "agency_code": "58"}, {"status": 0, "uuid": "5aeabaf7-0fbd-4931-a368-779d735db4b8", "agency_id": "48304", "agency_address": "", "agency_code": "89"}, {"status": 0, "uuid": "e83aff0b-0e4e-402f-ad03-77edfe8f5d51", "agency_id": "82390", "agency_address": "", "agency_code": "61"}, {"status": 0, "uuid": "21bc4753-22c1-4a6b-aa3d-f6de7dc041f0", "agency_id": "39777", "agency_address": "", "agency_code": "88"}, {"status": 0, "uuid": "ca000a1f-4e85-40bc-bff9-580c6b0cb8e7", "agency_id": "73992", "agency_address": "", "agency_code": "33"}, {"status": 0, "uuid": "b3c358e9-91a2-43ca-abd0-34ce9f5b27cb", "agency_id": "06556", "agency_address": "", "agency_code": "51"}, {"status": 0, "uuid": "c68f948a-1081-4d01-b2d1-8ff85b4596ed", "agency_id": "70745", "agency_address": "", "agency_code": "44"}, {"status": 0, "uuid": "57ce970f-9989-418e-a867-69efab566124", "agency_id": "71444", "agency_address": "", "agency_code": "35"}, {"status": 0, "uuid": "34ec6237-1fa9-426b-add0-2de0053e6eb4", "agency_id": "36081", "agency_address": "", "agency_code": "49"}, {"status": 0, "uuid": "b31ed289-6366-49f7-a343-ae4d4416fdf5", "agency_id": "75261", "agency_address": "", "agency_code": "50"}, {"status": 0, "uuid": "44345770-ef69-498b-8aba-5b66c57fd240", "agency_id": "83284", "agency_address": "", "agency_code": "26"}, {"status": 0, "uuid": "8927f30d-3707-4117-ba84-638469bbf230", "agency_id": "08502", "agency_address": "", "agency_code": "34"}, {"status": 0, "uuid": "5431e2e4-974e-4a22-ad1e-643138b5b1b8", "agency_id": "41640", "agency_address": "", "agency_code": "47"}, {"status": 0, "uuid": "5617468c-b3de-42f6-86ae-b23a9a411454", "agency_id": "87326", "agency_address": "", "agency_code": "45"}, {"status": 0, "uuid": "828b9bc6-0758-4a92-8098-64b2591200d4", "agency_id": "58859", "agency_address": "", "agency_code": "21"}, {"status": 0, "uuid": "71ef2e7d-6982-4fad-822b-81ee3ca76bd2", "agency_id": "10815", "agency_address": "", "agency_code": "69"}, {"status": 0, "uuid": "792867f7-539e-4355-a202-934fb01ced44", "agency_id": "42813", "agency_address": "", "agency_code": "06"}, {"status": 0, "uuid": "e8da8aa0-1e7d-4821-a17a-1b81afe7ab20", "agency_id": "03873", "agency_address": "", "agency_code": "04"}, {"status": 0, "uuid": "59e4742c-1bf7-4f3d-a305-4c3c9d09a7de", "agency_id": "87768", "agency_address": "", "agency_code": "16"}, {"status": 0, "uuid": "6aad8b1f-13e6-493c-84a7-915a226b6716", "agency_id": "73810", "agency_address": "", "agency_code": "86"}, {"status": 0, "uuid": "c005746b-ffdb-4d50-9b0c-42499eefa5b3", "agency_id": "64837", "agency_address": "", "agency_code": "85"}, {"status": 0, "uuid": "c3a17a7c-17e8-44d7-8f1e-f1d43db154ff", "agency_id": "32793", "agency_address": "", "agency_code": "09"}, {"status": 0, "uuid": "bdda8f66-820c-4bb1-a802-727538171f7b", "agency_id": "40703", "agency_address": "", "agency_code": "65"}, {"status": 0, "uuid": "55b4eff1-3a79-4d82-b210-98da845e7380", "agency_id": "89890", "agency_address": "", "agency_code": "91"}, {"status": 0, "uuid": "c46db476-d46f-48bc-b5c8-33209bc950f0", "agency_id": "12544", "agency_address": "", "agency_code": "90"}, {"status": 0, "uuid": "bbc109b8-95f5-413e-9700-a83f1bcdfeb1", "agency_id": "79473", "agency_address": "", "agency_code": "31"}, {"status": 0, "uuid": "0a3c8723-6f98-445d-8ae7-c97aebb640f7", "agency_id": "35507", "agency_address": "", "agency_code": "99"}, {"status": 0, "uuid": "32d3cfa6-6986-48db-959b-dd4dc8487cbe", "agency_id": "24489", "agency_address": "", "agency_code": "96"}, {"status": 0, "uuid": "b06911f9-37bf-4f83-a09d-b9c06288dac6", "agency_id": "07415", "agency_address": "", "agency_code": "75"}, {"status": 0, "uuid": "75bd1032-0694-456b-9020-dad535fa5391", "agency_id": "21996", "agency_address": "", "agency_code": "29"}, {"status": 0, "uuid": "2bf3d86e-0568-4534-a0e4-b0f274b46ec1", "agency_id": "59303", "agency_address": "", "agency_code": "05"}, {"status": 0, "uuid": "6cc3d8f5-1017-4f0b-93df-718d5b57a382", "agency_id": "95727", "agency_address": "", "agency_code": "77"}, {"status": 0, "uuid": "8948dab3-532a-4188-9f1d-2639c9a8bf54", "agency_id": "46720", "agency_address": "", "agency_code": "55"}, {"status": 0, "uuid": "0abe561a-704c-4588-af6b-c75846a84b7c", "agency_id": "08657", "agency_address": "", "agency_code": "98"}, {"status": 0, "uuid": "e6ce22fe-6970-42c2-8932-761fba18f750", "agency_id": "57166", "agency_address": "", "agency_code": "92"}, {"status": 0, "uuid": "7a2f55b5-607a-40ef-b665-72ea26902647", "agency_id": "94539", "agency_address": "", "agency_code": "62"}, {"status": 0, "uuid": "2ffb60a8-8aaf-4cdd-9910-46ac88a3ba81", "agency_id": "56539", "agency_address": "", "agency_code": "80"}, {"status": 0, "uuid": "620a9d49-42fa-43ca-9335-3f111566b409", "agency_id": "15305", "agency_address": "", "agency_code": "56"}, {"status": 0, "uuid": "b27ce329-01b8-4f75-aff4-066401c29788", "agency_id": "17740", "agency_address": "", "agency_code": "59"}, {"status": 0, "uuid": "8c722a9f-395e-4ca8-8839-af8f505d29fd", "agency_id": "28278", "agency_address": "", "agency_code": "23"}, {"status": 0, "uuid": "6c830fc6-ffb7-4e18-8c09-0dda4906a56b", "agency_id": "20969", "agency_address": "", "agency_code": "95"}, {"status": 0, "uuid": "60cc74a5-5d14-4166-b1e0-178cce87e66a", "agency_id": "16240", "agency_address": "", "agency_code": "20"}, {"status": 0, "uuid": "f3db8ead-3e54-4541-8b21-91ce2cbc478c", "agency_id": "48623", "agency_address": "", "agency_code": "12"}, {"status": 0, "uuid": "c5188df3-e2dd-49cd-88b3-b151686baa03", "agency_id": "01982", "agency_address": "", "agency_code": "17"}, {"status": 0, "uuid": "677695ab-8656-4d23-a3a5-923dcf0521bd", "agency_id": "09301", "agency_address": "", "agency_code": "64"}, {"status": 0, "uuid": "3a55ec27-0723-4a0f-b710-3bef8c32ed57", "agency_id": "03576", "agency_address": "", "agency_code": "48"}, {"status": 0, "uuid": "e5eeb9dd-f11a-469e-8245-623c9352ecd8", "agency_id": "38271", "agency_address": "", "agency_code": "01"}, {"status": 0, "uuid": "ab95adfc-d4f5-43a5-be8e-972ee7e40c37", "agency_id": "16320", "agency_address": "", "agency_code": "42"}, {"status": 0, "uuid": "c52ce792-ed54-42d5-bd23-3f1411b676c3", "agency_id": "73853", "agency_address": "", "agency_code": "18"}, {"status": 0, "uuid": "ac471665-eb96-4d64-8b59-3a5488f8f3a4", "agency_id": "87893", "agency_address": "", "agency_code": "74"}, {"status": 0, "uuid": "34e4cbad-83bd-4c34-9402-01bc8bce086f", "agency_id": "27025", "agency_address": "", "agency_code": "03"}, {"status": 0, "uuid": "e513e265-0088-474f-8af4-8e078817154d", "agency_id": "34513", "agency_address": "", "agency_code": "11"}, {"status": 0, "uuid": "2b80ceed-affe-4154-a392-c5e8abdccad6", "agency_id": "61208", "agency_address": "", "agency_code": "52"}, {"status": 0, "uuid": "f66f5dfc-ba71-40d9-a67f-a9805e739c2f", "agency_id": "10120", "agency_address": "", "agency_code": "14"}, {"status": 0, "uuid": "b046490b-213c-4268-9632-15e4d7b93a87", "agency_id": "42673", "agency_address": "", "agency_code": "82"}, {"status": 0, "uuid": "529e5ab7-da97-4d3d-90a8-ea468d0bbf9f", "agency_id": "36088", "agency_address": "", "agency_code": "72"}, {"status": 0, "uuid": "9ce5032d-619b-4183-a3f2-d1b7b2edf5f5", "agency_id": "37894", "agency_address": "", "agency_code": "22"}, {"status": 0, "uuid": "04de792a-f62e-4c74-80d6-93d99bbeea67", "agency_id": "92449", "agency_address": "", "agency_code": "02"}, {"status": 0, "uuid": "3a81e540-11ec-446e-bcf3-ea9418b4afda", "agency_id": "15993", "agency_address": "", "agency_code": "46"}, {"status": 0, "uuid": "d3452119-367d-4890-97f9-23f0b2b2633b", "agency_id": "30045", "agency_address": "", "agency_code": "63"}, {"status": 0, "uuid": "b69a7c63-d1a5-4158-b29b-02c6d3299796", "agency_id": "73203", "agency_address": "", "agency_code": "19"}, {"status": 0, "uuid": "84cd07d9-1274-4cda-9911-7ffa6ad9b503", "agency_id": "16673", "agency_address": "", "agency_code": "94"}, {"status": 0, "uuid": "e3af7acb-5c95-45b9-8613-d33995bf2264", "agency_id": "09577", "agency_address": "", "agency_code": "36"}, {"status": 0, "uuid": "20261042-c2de-4892-859b-69e9229968c1", "agency_id": "26047", "agency_address": "", "agency_code": "43"}, {"status": 0, "uuid": "d24f69df-467e-4fb9-844f-0992977e74b8", "agency_id": "85926", "agency_address": "", "agency_code": "10"}, {"status": 0, "uuid": "f0a933c8-131a-490e-bec6-cffcc1a856da", "agency_id": "47308", "agency_address": "", "agency_code": "79"}, {"status": 0, "uuid": "be449af1-e632-4557-978e-507a6148cd5f", "agency_id": "97671", "agency_address": "", "agency_code": "13"}, {"status": 0, "uuid": "903ca09e-b837-4873-8cb6-92c8178e7566", "agency_id": "26576", "agency_address": "", "agency_code": "71"}, {"status": 0, "uuid": "d7f403cc-14ee-4f99-b317-eb34d14fffd5", "agency_id": "24294", "agency_address": "", "agency_code": "97"}, {"status": 0, "uuid": "7d5added-aaa7-460c-ad58-4efb23b7ff9e", "agency_id": "51490", "agency_address": "", "agency_code": "81"}, {"status": 0, "uuid": "3c7369c7-5040-46ec-a819-2d3810202367", "agency_id": "02393", "agency_address": "", "agency_code": "08"}, {"status": 0, "uuid": "18017347-851c-4047-bd3a-840732e793c8", "agency_id": "78828", "agency_address": "", "agency_code": "37"}, {"status": 0, "uuid": "6957b247-053f-4c13-b5d3-81d941528b2e", "agency_id": "23592", "agency_address": "", "agency_code": "60"}, {"status": 0, "uuid": "f459a154-cd78-4d21-b575-03eec79e9481", "agency_id": "05319", "agency_address": "", "agency_code": "24"}, {"status": 0, "uuid": "e73c556d-b027-4f7f-8dc8-f6d0c16a05ae", "agency_id": "52575", "agency_address": "", "agency_code": "84"}, {"status": 0, "uuid": "2653377a-daa4-41ff-b896-b94732096bc5", "agency_id": "98498", "agency_address": "", "agency_code": "15"}, {"status": 0, "uuid": "d2cc9df8-a15f-49a0-a85c-5314cead48ba", "agency_id": "85999", "agency_address": "", "agency_code": "41"}, {"status": 0, "uuid": "741d6971-b060-4280-aa91-84e461f5c9cd", "agency_id": "86482", "agency_address": "", "agency_code": "70"}, {"status": 0, "uuid": "dc7a8a22-11e7-468c-9587-b46dab22246a", "agency_id": "04572", "agency_address": "", "agency_code": "66"}, {"status": 0, "uuid": "d40e746c-2b1b-4091-b9c7-1a40a700c0b3", "agency_id": "76149", "agency_address": "", "agency_code": "30"}, {"status": 0, "uuid": "ef97457e-4cc4-4ea1-813e-e886f1f12e83", "agency_id": "27213", "agency_address": "", "agency_code": "73"}, {"status": 0, "uuid": "16b3be82-d5ba-4348-9b22-90208599ca30", "agency_id": "92871", "agency_address": "", "agency_code": "68"}, {"status": 0, "uuid": "1ed3490d-865c-4136-be5c-ed3143ec4f5e", "agency_id": "45148", "agency_address": "", "agency_code": "40"}, {"status": 0, "uuid": "111a352b-ac58-49aa-a433-70d214d11f07", "agency_id": "72063", "agency_address": "", "agency_code": "39"}, {"status": 0, "uuid": "8221d37a-e9d1-43c8-807f-ebbc35670c1e", "agency_id": "04753", "agency_address": "", "agency_code": "38"}, {"status": 0, "uuid": "6494ad64-d62d-4365-a700-e1897d11d53a", "agency_id": "38617", "agency_address": "", "agency_code": "54"}, {"status": 0, "uuid": "20aa0320-62d9-4612-9ae9-8d611a1daca1", "agency_id": "70863", "agency_address": "", "agency_code": "27"}, {"status": 0, "uuid": "7ba3f64e-0819-4f92-a437-eb51d51f1aa4", "agency_id": "96807", "agency_address": "", "agency_code": "78"}, {"status": 0, "uuid": "07c8f7ea-3fdc-46ca-9e83-4a901c55cb8d", "agency_id": "18368", "agency_address": "", "agency_code": "85"}]}