{
                "status": 0,
                "uuid": "da4edf26-8e93-4b5b-9d50-d5732082fbcd",
                "zipcode": 46,
                "statecode": "32",
                "agencies": [
                                {
                                                "status": 0,
                                                "uuid": "4a4bc715-5d63-4c32-be3d-3f050b4fb870",
                                                "agency_id": "48079",
                                                "agency_address": "",
                                                "agency_code": "24"
                                },
                                {
                                                "status": 0,
                                                "uuid": "14ccf70d-44de-4b49-a0d0-7c5d4a5bda42",
                                                "agency_id": "82090",
                                                "agency_address": "",
                                                "agency_code": "91"
                                },
                                {
                                                "status": 0,
                                                "uuid": "b84ea60a-d618-4298-975c-a485cbe5945e",
                                                "agency_id": "83121",
                                                "agency_address": "",
                                                "agency_code": "60"
                                },
                                {
                                                "status": 0,
                                                "uuid": "34da274f-45fb-4129-befd-ad2f9dd618f0",
                                                "agency_id": "53910",
                                                "agency_address": "",
                                                "agency_code": "52"
                                },
                                {
                                                "status": 0,
                                                "uuid": "22868b45-dd7a-4408-a9c6-a87ba5e71f61",
                                                "agency_id": "42009",
                                                "agency_address": "",
                                                "agency_code": "26"
                                },
                                {
                                                "status": 0,
                                                "uuid": "0ab9bf03-c2ca-47a1-8fec-ab00aeca7013",
                                                "agency_id": "24704",
                                                "agency_address": "",
                                                "agency_code": "19"
                                },
                                {
                                                "status": 0,
                                                "uuid": "ea19a000-ad33-43df-b4fa-8a38dbe06245",
                                                "agency_id": "98082",
                                                "agency_address": "",
                                                "agency_code": "27"
                                },
                                {
                                                "status": 0,
                                                "uuid": "ebfb3fa2-fc96-4b16-b7fe-52305e3e653e",
                                                "agency_id": "87984",
                                                "agency_address": "",
                                                "agency_code": "57"
                                },
                                {
                                                "status": 0,
                                                "uuid": "ca1b7a94-89eb-43e7-b1a0-3bda25f56f71",
                                                "agency_id": "38647",
                                                "agency_address": "",
                                                "agency_code": "99"
                                },
                                {
                                                "status": 0,
                                                "uuid": "f4ef5b7c-2310-426f-9db9-1b2c6d23c035",
                                                "agency_id": "13455",
                                                "agency_address": "",
                                                "agency_code": "43"
                                },
                                {
                                                "status": 0,
                                                "uuid": "a76a3a0f-2497-4a46-b646-593a8fc1cdcb",
                                                "agency_id": "35607",
                                                "agency_address": "",
                                                "agency_code": "74"
                                },
                                {
                                                "status": 0,
                                                "uuid": "bb6df3f1-350c-4dc4-bff3-5702b3912a35",
                                                "agency_id": "06722",
                                                "agency_address": "",
                                                "agency_code": "63"
                                },
                                {
                                                "status": 0,
                                                "uuid": "61e720a1-3ed8-4565-8390-68e6d866c384",
                                                "agency_id": "91858",
                                                "agency_address": "",
                                                "agency_code": "87"
                                },
                                {
                                                "status": 0,
                                                "uuid": "40c73285-be19-4d36-a99e-de5740b59485",
                                                "agency_id": "45662",
                                                "agency_address": "",
                                                "agency_code": "65"
                                },
                                {
                                                "status": 0,
                                                "uuid": "d7db0b2c-03be-4749-ac5c-4bce9226336e",
                                                "agency_id": "01193",
                                                "agency_address": "",
                                                "agency_code": "70"
                                },
                                {
                                                "status": 0,
                                                "uuid": "3bdd8979-d800-491f-90ab-8dbce238ed4f",
                                                "agency_id": "37497",
                                                "agency_address": "",
                                                "agency_code": "02"
                                },
                                {
                                                "status": 0,
                                                "uuid": "9991634f-8edd-40fb-8f24-1b4005b2f648",
                                                "agency_id": "34515",
                                                "agency_address": "",
                                                "agency_code": "77"
                                },
                                {
                                                "status": 0,
                                                "uuid": "cc8d0245-709a-48aa-a120-3d2aba9d5b85",
                                                "agency_id": "87046",
                                                "agency_address": "",
                                                "agency_code": "13"
                                },
                                {
                                                "status": 0,
                                                "uuid": "b6f0ece1-bb36-47e3-8cc0-82266173986c",
                                                "agency_id": "36460",
                                                "agency_address": "",
                                                "agency_code": "39"
                                },
                                {
                                                "status": 0,
                                                "uuid": "fa2acb77-0ad3-47b5-8e0a-7c9d8518da6f",
                                                "agency_id": "61252",
                                                "agency_address": "",
                                                "agency_code": "16"
                                },
                                {
                                                "status": 0,
                                                "uuid": "90306b7e-7931-42cb-ba9f-7f33498744e3",
                                                "agency_id": "24811",
                                                "agency_address": "",
                                                "agency_code": "04"
                                },
                                {
                                                "status": 0,
                                                "uuid": "92841dc9-612f-406d-92e9-f0120407524c",
                                                "agency_id": "58486",
                                                "agency_address": "",
                                                "agency_code": "93"
                                },
                                {
                                                "status": 0,
                                                "uuid": "f4b75d36-01b4-4101-afa5-faf586282f11",
                                                "agency_id": "89898",
                                                "agency_address": "",
                                                "agency_code": "88"
                                },
                                {
                                                "status": 0,
                                                "uuid": "c4153504-297c-4764-85be-5fd5d3de490b",
                                                "agency_id": "10561",
                                                "agency_address": "",
                                                "agency_code": "11"
                                },
                                {
                                                "status": 0,
                                                "uuid": "2c216003-9cd7-49d6-bc7d-f81c7b2cccec",
                                                "agency_id": "90142",
                                                "agency_address": "",
                                                "agency_code": "50"
                                },
                                {
                                                "status": 0,
                                                "uuid": "ece328e0-8c85-4fa2-ba59-1d35a9335420",
                                                "agency_id": "09911",
                                                "agency_address": "",
                                                "agency_code": "68"
                                },
                                {
                                                "status": 0,
                                                "uuid": "56f423c0-539c-41f0-812a-5f4ec80a03e4",
                                                "agency_id": "40967",
                                                "agency_address": "",
                                                "agency_code": "59"
                                },
                                {
                                                "status": 0,
                                                "uuid": "21230264-8944-4c6c-943f-9b062db81e7b",
                                                "agency_id": "76285",
                                                "agency_address": "",
                                                "agency_code": "47"
                                },
                                {
                                                "status": 0,
                                                "uuid": "ddaa49ca-caac-4ec2-abfe-1ca5dbaa90d1",
                                                "agency_id": "04977",
                                                "agency_address": "",
                                                "agency_code": "71"
                                },
                                {
                                                "status": 0,
                                                "uuid": "4ee2294f-b917-41de-bd98-816cb40faa99",
                                                "agency_id": "61592",
                                                "agency_address": "",
                                                "agency_code": "33"
                                },
                                {
                                                "status": 0,
                                                "uuid": "6c8dbca2-c374-410c-b82c-56cdbbef78e1",
                                                "agency_id": "90527",
                                                "agency_address": "",
                                                "agency_code": "67"
                                },
                                {
                                                "status": 0,
                                                "uuid": "2b16c97e-43cb-46aa-8780-4461a2c852ef",
                                                "agency_id": "01928",
                                                "agency_address": "",
                                                "agency_code": "78"
                                },
                                {
                                                "status": 0,
                                                "uuid": "7512637d-fa92-4c76-8fb4-8938d07f08fa",
                                                "agency_id": "24250",
                                                "agency_address": "",
                                                "agency_code": "01"
                                },
                                {
                                                "status": 0,
                                                "uuid": "90a3c8dd-1266-4a83-8d5b-4dee2a41c592",
                                                "agency_id": "95970",
                                                "agency_address": "",
                                                "agency_code": "10"
                                },
                                {
                                                "status": 0,
                                                "uuid": "e43bf714-b409-4e23-86a5-0d0a8508bbf9",
                                                "agency_id": "57415",
                                                "agency_address": "",
                                                "agency_code": "76"
                                },
                                {
                                                "status": 0,
                                                "uuid": "e555bf6f-620f-4cbd-a557-b8b53f123076",
                                                "agency_id": "78315",
                                                "agency_address": "",
                                                "agency_code": "18"
                                },
                                {
                                                "status": 0,
                                                "uuid": "c2e95daa-ec4d-40bd-ba4d-5114258f2d8a",
                                                "agency_id": "65171",
                                                "agency_address": "",
                                                "agency_code": "15"
                                },
                                {
                                                "status": 0,
                                                "uuid": "5d67181b-56d0-4dc4-a272-9a203d467c57",
                                                "agency_id": "68148",
                                                "agency_address": "",
                                                "agency_code": "48"
                                },
                                {
                                                "status": 0,
                                                "uuid": "5f35e6f3-e6b6-4677-a7a6-0d5f982182c2",
                                                "agency_id": "52166",
                                                "agency_address": "",
                                                "agency_code": "08"
                                },
                                {
                                                "status": 0,
                                                "uuid": "1c4bac3a-bdd8-41f3-8a66-3c58f9e82683",
                                                "agency_id": "43533",
                                                "agency_address": "",
                                                "agency_code": "46"
                                },
                                {
                                                "status": 0,
                                                "uuid": "a2507783-0d36-4e25-a2d7-78ebb1612ece",
                                                "agency_id": "49483",
                                                "agency_address": "",
                                                "agency_code": "28"
                                },
                                {
                                                "status": 0,
                                                "uuid": "5d85e89d-f5f2-414e-88d9-03c516fe09a1",
                                                "agency_id": "90171",
                                                "agency_address": "",
                                                "agency_code": "92"
                                },
                                {
                                                "status": 0,
                                                "uuid": "6bb07bec-55a5-43ae-bd34-be5096bc3295",
                                                "agency_id": "83846",
                                                "agency_address": "",
                                                "agency_code": "41"
                                },
                                {
                                                "status": 0,
                                                "uuid": "86cba055-6a19-4943-9938-fb89e68cb496",
                                                "agency_id": "23875",
                                                "agency_address": "",
                                                "agency_code": "89"
                                },
                                {
                                                "status": 0,
                                                "uuid": "a068419c-c6ee-43f6-be88-ec7b2f4af0c5",
                                                "agency_id": "76944",
                                                "agency_address": "",
                                                "agency_code": "05"
                                },
                                {
                                                "status": 0,
                                                "uuid": "c7275572-c738-4ac1-a50c-6fec42a6fb92",
                                                "agency_id": "52797",
                                                "agency_address": "",
                                                "agency_code": "56"
                                },
                                {
                                                "status": 0,
                                                "uuid": "bf0a69b4-1286-43d3-9026-e862c7956bb8",
                                                "agency_id": "02210",
                                                "agency_address": "",
                                                "agency_code": "45"
                                },
                                {
                                                "status": 0,
                                                "uuid": "c34b453d-b383-49d2-836a-1a029401b187",
                                                "agency_id": "45692",
                                                "agency_address": "",
                                                "agency_code": "62"
                                },
                                {
                                                "status": 0,
                                                "uuid": "5f4e0775-4b3b-422f-970b-01bd2be3f260",
                                                "agency_id": "64500",
                                                "agency_address": "",
                                                "agency_code": "95"
                                },
                                {
                                                "status": 0,
                                                "uuid": "adc21903-ce73-4e50-9b07-45cc3556b4da",
                                                "agency_id": "70760",
                                                "agency_address": "",
                                                "agency_code": "75"
                                },
                                {
                                                "status": 0,
                                                "uuid": "16f9ddca-1b99-421d-8451-9f91d99f39c1",
                                                "agency_id": "97458",
                                                "agency_address": "",
                                                "agency_code": "61"
                                },
                                {
                                                "status": 0,
                                                "uuid": "58793669-ec5f-4a0f-922d-af529945ced7",
                                                "agency_id": "18170",
                                                "agency_address": "",
                                                "agency_code": "53"
                                },
                                {
                                                "status": 0,
                                                "uuid": "c662fa0c-1306-403d-a7f3-82ffff35b883",
                                                "agency_id": "15252",
                                                "agency_address": "",
                                                "agency_code": "30"
                                },
                                {
                                                "status": 0,
                                                "uuid": "d9fadcc3-45e9-470b-a1ab-1d122588c4f5",
                                                "agency_id": "15859",
                                                "agency_address": "",
                                                "agency_code": "09"
                                },
                                {
                                                "status": 0,
                                                "uuid": "01833f2f-bec1-4210-8d03-48c8d56c05b2",
                                                "agency_id": "83146",
                                                "agency_address": "",
                                                "agency_code": "55"
                                },
                                {
                                                "status": 0,
                                                "uuid": "d49a5b84-4523-48d6-b2c2-0a2bfa805e6a",
                                                "agency_id": "57709",
                                                "agency_address": "",
                                                "agency_code": "90"
                                },
                                {
                                                "status": 0,
                                                "uuid": "10384ae0-15c4-4dd5-9bb2-a080ef244d96",
                                                "agency_id": "92412",
                                                "agency_address": "",
                                                "agency_code": "80"
                                },
                                {
                                                "status": 0,
                                                "uuid": "1acd48e3-671c-4011-98de-0885f1ae8a77",
                                                "agency_id": "26428",
                                                "agency_address": "",
                                                "agency_code": "17"
                                },
                                {
                                                "status": 0,
                                                "uuid": "9efd8e8f-785c-47fd-939f-33a8e009a39c",
                                                "agency_id": "81479",
                                                "agency_address": "",
                                                "agency_code": "07"
                                },
                                {
                                                "status": 0,
                                                "uuid": "5b83f255-9aed-48d8-a756-dfa3b81e094d",
                                                "agency_id": "90333",
                                                "agency_address": "",
                                                "agency_code": "85"
                                },
                                {
                                                "status": 0,
                                                "uuid": "0b4628ea-fa84-441e-87ce-0456473b3b5a",
                                                "agency_id": "94101",
                                                "agency_address": "",
                                                "agency_code": "84"
                                },
                                {
                                                "status": 0,
                                                "uuid": "a98e8311-4dd1-4375-a557-ef5db6679f6f",
                                                "agency_id": "75813",
                                                "agency_address": "",
                                                "agency_code": "37"
                                },
                                {
                                                "status": 0,
                                                "uuid": "8b091d22-99d5-4f26-a6b6-99cc08612481",
                                                "agency_id": "73215",
                                                "agency_address": "",
                                                "agency_code": "51"
                                },
                                {
                                                "status": 0,
                                                "uuid": "cd0808d8-9e15-4887-af1f-a76421bff27e",
                                                "agency_id": "15853",
                                                "agency_address": "",
                                                "agency_code": "42"
                                },
                                {
                                                "status": 0,
                                                "uuid": "7c8fa045-2471-45d0-a19f-aa951eec9f5e",
                                                "agency_id": "24547",
                                                "agency_address": "",
                                                "agency_code": "14"
                                },
                                {
                                                "status": 0,
                                                "uuid": "0a1b7533-1cdc-4c6f-ba62-6b5eab6f115e",
                                                "agency_id": "26153",
                                                "agency_address": "",
                                                "agency_code": "58"
                                },
                                {
                                                "status": 0,
                                                "uuid": "1859e1e1-efc5-411e-a43d-19be6755449f",
                                                "agency_id": "79289",
                                                "agency_address": "",
                                                "agency_code": "20"
                                },
                                {
                                                "status": 0,
                                                "uuid": "50851ae1-614c-4651-ba8e-7b22c9f4c2f2",
                                                "agency_id": "53789",
                                                "agency_address": "",
                                                "agency_code": "54"
                                },
                                {
                                                "status": 0,
                                                "uuid": "9858fb10-ee35-487f-a5dc-eaac574209dc",
                                                "agency_id": "01468",
                                                "agency_address": "",
                                                "agency_code": "23"
                                },
                                {
                                                "status": 0,
                                                "uuid": "464cb650-85a5-4558-bfdc-5eff68c794d8",
                                                "agency_id": "72004",
                                                "agency_address": "",
                                                "agency_code": "98"
                                },
                                {
                                                "status": 0,
                                                "uuid": "23b0cb0f-1c23-4c32-af9d-8acebaea4101",
                                                "agency_id": "59271",
                                                "agency_address": "",
                                                "agency_code": "40"
                                },
                                {
                                                "status": 0,
                                                "uuid": "3a43a909-8455-4eed-a715-1b90f873295d",
                                                "agency_id": "13988",
                                                "agency_address": "",
                                                "agency_code": "72"
                                },
                                {
                                                "status": 0,
                                                "uuid": "3a3c33cc-e648-4af9-8a53-cc1595515a89",
                                                "agency_id": "21150",
                                                "agency_address": "",
                                                "agency_code": "44"
                                },
                                {
                                                "status": 0,
                                                "uuid": "55d95f3e-db99-46ac-acb6-727d0f0a74a4",
                                                "agency_id": "24130",
                                                "agency_address": "",
                                                "agency_code": "69"
                                },
                                {
                                                "status": 0,
                                                "uuid": "2bb1e332-0afa-4a71-bc68-a61d04e174fd",
                                                "agency_id": "98451",
                                                "agency_address": "",
                                                "agency_code": "32"
                                },
                                {
                                                "status": 0,
                                                "uuid": "52a8d853-5fe6-43a3-ba08-6853dada2b62",
                                                "agency_id": "57328",
                                                "agency_address": "",
                                                "agency_code": "36"
                                },
                                {
                                                "status": 0,
                                                "uuid": "3001193e-10e6-4e25-bb61-c69e4487d80b",
                                                "agency_id": "14915",
                                                "agency_address": "",
                                                "agency_code": "49"
                                },
                                {
                                                "status": 0,
                                                "uuid": "f5da30d8-ce8b-4529-a386-4163e36ba93a",
                                                "agency_id": "79434",
                                                "agency_address": "",
                                                "agency_code": "34"
                                },
                                {
                                                "status": 0,
                                                "uuid": "e2bf0b31-4d81-4ced-a1ac-e41ccf6061e9",
                                                "agency_id": "68188",
                                                "agency_address": "",
                                                "agency_code": "96"
                                },
                                {
                                                "status": 0,
                                                "uuid": "e85e9f0b-a2da-4f25-a7df-27959515a631",
                                                "agency_id": "98168",
                                                "agency_address": "",
                                                "agency_code": "66"
                                },
                                {
                                                "status": 0,
                                                "uuid": "421ba386-e157-4610-88e9-9880c4844bf8",
                                                "agency_id": "83813",
                                                "agency_address": "",
                                                "agency_code": "38"
                                },
                                {
                                                "status": 0,
                                                "uuid": "df999517-301a-4430-bf8a-2e4af8c83e5d",
                                                "agency_id": "06655",
                                                "agency_address": "",
                                                "agency_code": "22"
                                },
                                {
                                                "status": 0,
                                                "uuid": "e231563b-594f-4f35-b174-e21492953dae",
                                                "agency_id": "21004",
                                                "agency_address": "",
                                                "agency_code": "73"
                                },
                                {
                                                "status": 0,
                                                "uuid": "54a74c9a-d4bb-4675-82fd-1355168a886c",
                                                "agency_id": "38603",
                                                "agency_address": "",
                                                "agency_code": "82"
                                },
                                {
                                                "status": 0,
                                                "uuid": "91b2c98e-c4a3-4b6f-b3f7-07c32a35add9",
                                                "agency_id": "51207",
                                                "agency_address": "",
                                                "agency_code": "64"
                                },
                                {
                                                "status": 0,
                                                "uuid": "e8a82d44-eb4c-45d6-bb2b-14f242d798cc",
                                                "agency_id": "73206",
                                                "agency_address": "",
                                                "agency_code": "83"
                                },
                                {
                                                "status": 0,
                                                "uuid": "3c3ddd5d-b87d-4a3b-a673-874965408bfe",
                                                "agency_id": "60590",
                                                "agency_address": "",
                                                "agency_code": "79"
                                },
                                {
                                                "status": 0,
                                                "uuid": "011fda28-c7c2-4f3f-aebd-3366757e3e3d",
                                                "agency_id": "06618",
                                                "agency_address": "",
                                                "agency_code": "97"
                                },
                                {
                                                "status": 0,
                                                "uuid": "02a6c60a-188a-4994-814f-b34de9205536",
                                                "agency_id": "52574",
                                                "agency_address": "",
                                                "agency_code": "21"
                                },
                                {
                                                "status": 0,
                                                "uuid": "19ad29fb-eaad-4f25-8e47-308e739c029a",
                                                "agency_id": "67458",
                                                "agency_address": "",
                                                "agency_code": "35"
                                },
                                {
                                                "status": 0,
                                                "uuid": "ed1b556b-9aeb-4464-b08d-a0afea90bdb7",
                                                "agency_id": "14361",
                                                "agency_address": "",
                                                "agency_code": "25"
                                },
                                {
                                                "status": 0,
                                                "uuid": "29ac4669-141f-4681-a88f-038a7a03027b",
                                                "agency_id": "40332",
                                                "agency_address": "",
                                                "agency_code": "94"
                                },
                                {
                                                "status": 0,
                                                "uuid": "73a1f1ae-789b-40d0-ab78-58abb01fdac4",
                                                "agency_id": "75300",
                                                "agency_address": "",
                                                "agency_code": "06"
                                },
                                {
                                                "status": 0,
                                                "uuid": "4cd8635f-936d-46c4-aa62-41b79f992e6d",
                                                "agency_id": "79028",
                                                "agency_address": "",
                                                "agency_code": "29"
                                },
                                {
                                                "status": 0,
                                                "uuid": "6f5c019d-8aeb-4453-aea1-3b8c04d05b2b",
                                                "agency_id": "13799",
                                                "agency_address": "",
                                                "agency_code": "31"
                                },
                                {
                                                "status": 0,
                                                "uuid": "3659286d-ce92-4321-a298-150cd6faf827",
                                                "agency_id": "10341",
                                                "agency_address": "",
                                                "agency_code": "86"
                                },
                                {
                                                "status": 0,
                                                "uuid": "a80427b7-449b-4b5e-8fad-ac272adc2782",
                                                "agency_id": "70708",
                                                "agency_address": "",
                                                "agency_code": "03"
                                },
                                {
                                                "status": 0,
                                                "uuid": "6ef7db9f-a34c-4599-8339-56bf27f0a743",
                                                "agency_id": "50485",
                                                "agency_address": "",
                                                "agency_code": "12"
                                },
                                {
                                                "status": 0,
                                                "uuid": "0244e091-9919-4e29-b79e-0517931e727b",
                                                "agency_id": "74858",
                                                "agency_address": "",
                                                "agency_code": "15"
                                }
                ]
}